dataset_encoder/__init__.py
dataset_encoder/__version__.py
dataset_encoder/categorical_encoder.py
dataset_encoder/circular_encoder.py
dataset_encoder/datetime_encoder.py
dataset_encoder/encoder.py
dataset_encoder/numerical_encoder.py
dataset_encoder-1.0.0.dist-info/LICENSE
dataset_encoder-1.0.0.dist-info/METADATA
dataset_encoder-1.0.0.dist-info/WHEEL
dataset_encoder-1.0.0.dist-info/top_level.txt
dataset_encoder-1.0.0.dist-info/RECORD
