Metadata-Version: 2.1
Name: dataset_encoder
Version: 1.0.0
Summary: Transform your preprocessing stage into a fully automated process!
Author-email: dmforit <dmitrykaratyshchev@gmail.com>
License: Apache License
Project-URL: Homepage, https://github.com/dmforit/auto-dataset-encoder
Keywords: automl,encoder,dataset_encoder,encode,auto,dataset,feature,type,inference
Classifier: Programming Language :: Python :: 3
Classifier: Operating System :: OS Independent
Requires-Python: >=3.8
License-File: LICENSE
Requires-Dist: category-encoders >=2.6.3
Requires-Dist: numpy >=1.25.2
Requires-Dist: pandas >=2.0
Requires-Dist: scikit-learn >=1.2.2
Requires-Dist: scipy >=1.11.4
